worklogi/__init__.py
worklogi/__main__.py
worklogi/add_entry.py
worklogi/browse_entries.py
worklogi/database.py
worklogi/entry.py
worklogi/main.py
worklogi-0.2.1.dist-info/LICENSE
worklogi-0.2.1.dist-info/METADATA
worklogi-0.2.1.dist-info/WHEEL
worklogi-0.2.1.dist-info/entry_points.txt
worklogi-0.2.1.dist-info/RECORD
